CHANGES.rst
MANIFEST.in
README.rst
requirements.txt
setup.py
python_space.egg-info/PKG-INFO
python_space.egg-info/SOURCES.txt
python_space.egg-info/dependency_links.txt
python_space.egg-info/entry_points.txt
python_space.egg-info/not-zip-safe
python_space.egg-info/requires.txt
python_space.egg-info/top_level.txt
space/__init__.py
space/main.py
space/util.py
space/modules/__init__.py
space/modules/activationkey.py
space/modules/api.py
space/modules/channel.py
space/modules/packages.py
space/modules/system.py